[{"GEOID":"54063","adj":[9,39],"pop":12376,"county":"063","weights":[2,2]},{"GEOID":"54037","adj":[24],"pop":57701,"county":"037","weights":[32]},{"GEOID":"54047","adj":[4,10,53],"pop":19111,"county":"047","weights":[2,32,2]},{"GEOID":"54005","adj":[4,14,19,28,36],"pop":21809,"county":"005","weights":[2,2,32,2,2]},{"GEOID":"54109","adj":[2,3,10,14,36,53],"pop":21382,"county":"109","weights":[2,2,2,32,2,2]},{"GEOID":"54083","adj":[20,22,25,33,34,48,50],"pop":27932,"county":"083","weights":[2,2,2,2,32,2,2]},{"GEOID":"54065","adj":[11,24],"pop":17063,"county":"065","weights":[2,2]},{"GEOID":"54107","adj":[12,21,40,51],"pop":84296,"county":"107","weights":[2,2,2,2]},{"GEOID":"54103","adj":[13,16,35,41,44,46],"pop":14442,"county":"103","weights":[2,2,2,2,2,2]},{"GEOID":"54025","adj":[0,17,18,33,39,50],"pop":32977,"county":"025","weights":[2,2,2,2,2,2]},{"GEOID":"54059","adj":[2,4,14,19,30],"pop":23568,"county":"059","weights":[2,2,2,2,2]},{"GEOID":"54027","adj":[6,26,27],"pop":23093,"county":"027","weights":[2,2,2]},{"GEOID":"54073","adj":[7,21,35],"pop":7653,"county":"073","weights":[2,2,2]},{"GEOID":"54049","adj":[8,16,38,41],"pop":56205,"county":"049","weights":[2,2,2,2]},{"GEOID":"54045","adj":[3,4,10,19],"pop":32567,"county":"045","weights":[2,2,2,2]},{"GEOID":"54087","adj":[28,40,47,49,51],"pop":14028,"county":"087","weights":[2,2,2,2,2]},{"GEOID":"54033","adj":[8,13,20,38,45,46,48],"pop":65921,"county":"033","weights":[2,2,2,2,2,2,2]},{"GEOID":"54067","adj":[9,18,28,31,49,50],"pop":24604,"county":"067","weights":[2,2,2,2,2,2]},{"GEOID":"54019","adj":[9,17,28,36,39],"pop":40488,"county":"019","weights":[2,2,2,2,2]},{"GEOID":"54043","adj":[3,10,14,28,29,30,54],"pop":20463,"county":"043","weights":[2,2,2,2,2,2,2]},{"GEOID":"54001","adj":[5,16,34,38,42,48],"pop":15465,"county":"001","weights":[2,2,2,2,2,2]},{"GEOID":"54085","adj":[7,12,23,35,40,46,47],"pop":8444,"county":"085","weights":[2,2,2,2,2,2,2]},{"GEOID":"54023","adj":[5,25,26,27,34,42],"pop":10976,"county":"023","weights":[2,2,2,2,2,2]},{"GEOID":"54021","adj":[21,31,45,46,47],"pop":7408,"county":"021","weights":[2,2,2,2,2]},{"GEOID":"54003","adj":[1,6],"pop":122076,"county":"003","weights":[2,2]},{"GEOID":"54071","adj":[5,22,27,33],"pop":6143,"county":"071","weights":[2,2,2,2]},{"GEOID":"54057","adj":[11,22],"pop":26938,"county":"057","weights":[2,2]},{"GEOID":"54031","adj":[11,22,25],"pop":14299,"county":"031","weights":[2,2,2]},{"GEOID":"54039","adj":[3,15,17,18,19,36,49,51,54],"pop":180745,"county":"039","weights":[2,2,2,2,2,2,2,2,2]},{"GEOID":"54011","adj":[19,30,32,54],"pop":94350,"county":"011","weights":[2,2,2,2]},{"GEOID":"54099","adj":[10,19,29],"pop":38982,"county":"099","weights":[2,2,2]},{"GEOID":"54007","adj":[17,23,45,47,49,50],"pop":12447,"county":"007","weights":[2,2,2,2,2,2]},{"GEOID":"54053","adj":[29,51,54],"pop":25453,"county":"053","weights":[2,2,2]},{"GEOID":"54075","adj":[5,9,25,50],"pop":7869,"county":"075","weights":[2,2,2,2]},{"GEOID":"54093","adj":[5,20,22,42],"pop":6762,"county":"093","weights":[2,2,2,2]},{"GEOID":"54095","adj":[8,12,21,46],"pop":8313,"county":"095","weights":[2,2,2,2]},{"GEOID":"54081","adj":[3,4,18,28,39,53],"pop":74591,"county":"081","weights":[2,2,2,2,2,2]},{"GEOID":"54029","adj":[52],"pop":29095,"county":"029","weights":[2]},{"GEOID":"54091","adj":[13,16,20,41,42],"pop":16705,"county":"091","weights":[2,2,2,2,2]},{"GEOID":"54089","adj":[0,9,18,36,53],"pop":11959,"county":"089","weights":[2,2,2,2,2]},{"GEOID":"54105","adj":[7,15,21,47,51],"pop":5194,"county":"105","weights":[2,2,2,2,2]},{"GEOID":"54061","adj":[8,13,38,42],"pop":105822,"county":"061","weights":[2,2,2,2]},{"GEOID":"54077","adj":[20,22,34,38,41],"pop":34216,"county":"077","weights":[2,2,2,2,2]},{"GEOID":"54069","adj":[44,52],"pop":42425,"county":"069","weights":[2,2]},{"GEOID":"54051","adj":[8,43],"pop":30591,"county":"051","weights":[2,2]},{"GEOID":"54041","adj":[16,23,31,46,48,50],"pop":17033,"county":"041","weights":[2,2,2,2,2,2]},{"GEOID":"54017","adj":[8,16,21,23,35,45],"pop":7808,"county":"017","weights":[2,2,2,2,2,2]},{"GEOID":"54013","adj":[15,21,23,31,40,49],"pop":6229,"county":"013","weights":[2,2,2,2,2,2]},{"GEOID":"54097","adj":[5,16,20,45,50],"pop":23816,"county":"097","weights":[2,2,2,2,2]},{"GEOID":"54015","adj":[15,17,28,31,47],"pop":8051,"county":"015","weights":[2,2,2,2,2]},{"GEOID":"54101","adj":[5,9,17,31,33,45,48],"pop":8378,"county":"101","weights":[2,2,2,2,2,2,2]},{"GEOID":"54035","adj":[7,15,28,32,40,54],"pop":27791,"county":"035","weights":[2,2,2,2,2,2]},{"GEOID":"54009","adj":[37,43],"pop":22559,"county":"009","weights":[2,2]},{"GEOID":"54055","adj":[2,4,36,39],"pop":59664,"county":"055","weights":[2,2,2,2]},{"GEOID":"54079","adj":[19,28,29,32,51],"pop":57440,"county":"079","weights":[2,2,2,2,2]}]
